chess/__init__.py
chess/engine.py
chess/gaviota.py
chess/pgn.py
chess/polyglot.py
chess/svg.py
chess/syzygy.py
chess/variant.py
python_chess_bughouse-0.28.0.dist-info/LICENSE.txt
python_chess_bughouse-0.28.0.dist-info/METADATA
python_chess_bughouse-0.28.0.dist-info/WHEEL
python_chess_bughouse-0.28.0.dist-info/top_level.txt
python_chess_bughouse-0.28.0.dist-info/RECORD
