Metadata-Version: 2.1
Name: python-chess-bughouse
Version: 0.28.0
Summary: A pure Python chess library with move generation and validation, Polyglot opening book probing, PGN reading and writing, Gaviota tablebase probing, Syzygy tablebase probing and XBoard/UCI engine communication.
Home-page: https://github.com/niklasf/python-chess
Author: Niklas Fiekas
Author-email: niklas.fiekas@backscattering.de
License: GPL-3.0+
Keywords: chess fen epd pgn polyglot syzygy gaviota uci xboard bughouse
Classifier: Development Status :: 5 - Production/Stable
Classifier: Intended Audience :: Developers
Classifier: Intended Audience :: Science/Research
Classifier: License :: OSI Approved :: GNU General Public License v3 or later (GPLv3+)
Classifier: Operating System :: OS Independent
Classifier: Programming Language :: Python
Classifier: Programming Language :: Python :: 3
Classifier: Programming Language :: Python :: 3.5
Classifier: Programming Language :: Python :: 3.6
Classifier: Programming Language :: Python :: 3.7
Classifier: Programming Language :: Python :: 3 :: Only
Classifier: Topic :: Games/Entertainment :: Board Games
Classifier: Topic :: Software Development :: Libraries :: Python Modules
Requires-Python: >=3.5
License-File: LICENSE.txt
